QTNOME/QTNOME.py
QTNOME_P_Y_R_O_B_O_T-1.0.5.dist-info/LICENSE
QTNOME_P_Y_R_O_B_O_T-1.0.5.dist-info/METADATA
QTNOME_P_Y_R_O_B_O_T-1.0.5.dist-info/WHEEL
QTNOME_P_Y_R_O_B_O_T-1.0.5.dist-info/top_level.txt
QTNOME_P_Y_R_O_B_O_T-1.0.5.dist-info/RECORD
