Metadata-Version: 2.1
Name: QTNOME-P-Y-R-O-B-O-T
Version: 1.0.5
Summary: An multiwindowed application envirement made in PyQt
Author-email: KUSHAL <NONE@NONE.com>
License: GNU GENERAL PUBLIC LICENSE
Project-URL: Homepage, https://github.com/P-Y-R-O-B-O-T/QTNOME
Keywords: UI,Envirement,QT,PyQt,UI Envirement,Desktop application
Requires-Python: >=3.10
License-File: LICENSE
Requires-Dist: PyQt5
